swissdta/__init__.py
swissdta/constants.py
swissdta/fields.py
swissdta/file.py
swissdta/util.py
swissdta/records/__init__.py
swissdta/records/common.py
swissdta/records/header.py
swissdta/records/record.py
swissdta/records/record836.py
swissdta/records/record890.py
swissdta-1.0.1.dist-info/DESCRIPTION.rst
swissdta-1.0.1.dist-info/METADATA
swissdta-1.0.1.dist-info/RECORD
swissdta-1.0.1.dist-info/WHEEL
swissdta-1.0.1.dist-info/metadata.json
swissdta-1.0.1.dist-info/top_level.txt
tests/__init__.py
tests/test_field.py
tests/test_field_alphanumeric.py
tests/test_field_amount.py
tests/test_field_currency.py
tests/test_field_date.py
tests/test_field_iban.py
tests/test_field_numeric.py
tests/test_file.py
tests/test_record.py
tests/test_util.py
