Metadata-Version: 2.0
Name: swissdta
Version: 1.0.1
Summary: Swiss DTA payment record (TA 836) generator library
Home-page: https://github.com/BitySA/swissdta
Author: Jacques Dafflon
Author-email: jacques.dafflon@gmail.com
License: MIT
Platform: UNKNOWN
Classifier: Development Status :: 5 - Production/Stable
Classifier: Intended Audience :: Developers
Classifier: Intended Audience :: Financial and Insurance Industry
Classifier: License :: OSI Approved :: MIT License
Classifier: Operating System :: OS Independent
Classifier: Programming Language :: Python :: 3.6
Classifier: Topic :: Office/Business :: Financial
Classifier: Topic :: Office/Business :: Financial :: Accounting
Classifier: Topic :: Software Development :: Libraries :: Python Modules
Requires-Dist: iso4217
Requires-Dist: schwifty
